ssdeep/__about__.py
ssdeep/__init__.py
ssdeep/_build.py
ssdeep/_libfuzzy.abi3.so
ssdeep/py.typed
ssdeep_wheel-3.4.1.post1.dist-info/LICENSE
ssdeep_wheel-3.4.1.post1.dist-info/METADATA
ssdeep_wheel-3.4.1.post1.dist-info/WHEEL
ssdeep_wheel-3.4.1.post1.dist-info/top_level.txt
ssdeep_wheel-3.4.1.post1.dist-info/RECORD
