Metadata-Version: 2.1
Name: ssdeep-wheel
Version: 3.4.1.post1
Summary: Python wrapper for the ssdeep library
Home-page: https://github.com/hzqmwne/python-ssdeep
Author: PhiBo (DinoTools)
License: LGPLv3+
Project-URL: Upstream, http://github.com/DinoTools/python-ssdeep
Keywords: ssdeep
Platform: UNKNOWN
Classifier: Development Status :: 5 - Production/Stable
Classifier: Intended Audience :: Developers
Classifier: License :: OSI Approved :: GNU Lesser General Public License v3 or later (LGPLv3+)
Classifier: Operating System :: OS Independent
Classifier: Programming Language :: Python
Classifier: Programming Language :: Python :: 3.6
Classifier: Programming Language :: Python :: 3.7
Classifier: Programming Language :: Python :: 3.8
Classifier: Programming Language :: Python :: 3.9
Classifier: Programming Language :: Python :: 3.10
Classifier: Programming Language :: Python :: 3.11
Classifier: Programming Language :: Python :: 3.12
Classifier: Programming Language :: Python :: 3.13
Classifier: Programming Language :: Python :: 3.14
Classifier: Programming Language :: Python :: Implementation :: CPython
Classifier: Programming Language :: Python :: Implementation :: PyPy
Classifier: Topic :: Software Development :: Libraries :: Python Modules
Requires-Python: >=3.6
License-File: LICENSE
Requires-Dist: cffi (>=1.0.0)
Provides-Extra: docstest
Requires-Dist: doc8 ; extra == 'docstest'
Requires-Dist: readme-renderer (>=16.0) ; extra == 'docstest'
Requires-Dist: sphinx ; extra == 'docstest'
Requires-Dist: sphinx-rtd-theme ; extra == 'docstest'
